tsaugmentation/__init__.py
tsaugmentation/feature_engineering/__init__.py
tsaugmentation/feature_engineering/dynamic_features.py
tsaugmentation/feature_engineering/feature_transformations.py
tsaugmentation/feature_engineering/get_data_distance.py
tsaugmentation/feature_engineering/static_features.py
tsaugmentation/model/__init__.py
tsaugmentation/model/create_dataset_versions_vae.py
tsaugmentation/model/helper.py
tsaugmentation/model/hyperparameter_tuning.py
tsaugmentation/model/models.py
tsaugmentation/postprocessing/__init__.py
tsaugmentation/postprocessing/generative_helper.py
tsaugmentation/preprocessing/__init__.py
tsaugmentation/preprocessing/pre_processing_datasets.py
tsaugmentation/preprocessing/subsample_dataset.py
tsaugmentation/preprocessing/utils.py
tsaugmentation/tests/__init__.py
tsaugmentation/tests/manipulate_cvae.py
tsaugmentation/tests/test_building_distances_plots.py
tsaugmentation/tests/test_compute_similarities.py
tsaugmentation/tests/test_create_groups_class.py
tsaugmentation/tests/test_create_subsampled_dataset.py
tsaugmentation/tests/test_create_synthetic_data.py
tsaugmentation/tests/test_create_transformed_dataset_files.py
tsaugmentation/tests/test_end2end_vae_police.py
tsaugmentation/tests/test_end2end_vae_prison.py
tsaugmentation/tests/test_end2end_vae_tourism.py
tsaugmentation/tests/test_evaluate_similarity_dataset_w_groups.py
tsaugmentation/tests/test_feature_engineering.py
tsaugmentation/tests/test_hyparparameter_tuning_vae.py
tsaugmentation/tests/test_import_datasets.py
tsaugmentation/tests/test_load_complete_m5.py
tsaugmentation/tests/test_manipulate_data.py
tsaugmentation/tests/test_similarity_ts.py
tsaugmentation/tests/test_vae_test_size.py
tsaugmentation/tests/test_visualize_transformed_datasets.py
tsaugmentation/transformations/__init__.py
tsaugmentation/transformations/compute_distances.py
tsaugmentation/transformations/compute_similarities.py
tsaugmentation/transformations/compute_similarities_summary_metrics.py
tsaugmentation-0.5.69.dist-info/LICENSE
tsaugmentation-0.5.69.dist-info/METADATA
tsaugmentation-0.5.69.dist-info/WHEEL
tsaugmentation-0.5.69.dist-info/top_level.txt
tsaugmentation-0.5.69.dist-info/RECORD
